{
    "key": "group_5f5fbaab2217b",
    "title": "Page - Free Estimate",
    "fields": [
        {
            "key": "field_5fbd40ac9333d",
            "label": "Free Estimate Form Content Left",
            "name": "free_estimate_form_content_left",
            "type": "clone",
            "instructions": "",
            "required": 0,
            "conditional_logic": 0,
            "wrapper": {
                "width": "",
                "class": "",
                "id": ""
            },
            "clone": [
                "group_5faeda2433091"
            ],
            "display": "seamless",
            "layout": "block",
            "prefix_label": 0,
            "prefix_name": 0
        },
        {
            "key": "field_5fbd40e79333e",
            "label": "Free Estimate Image Content Right",
            "name": "free_estimate_image_content_right",
            "type": "clone",
            "instructions": "",
            "required": 0,
            "conditional_logic": 0,
            "wrapper": {
                "width": "",
                "class": "",
                "id": ""
            },
            "clone": [
                "group_5f74dec6cb62e"
            ],
            "display": "seamless",
            "layout": "block",
            "prefix_label": 0,
            "prefix_name": 0
        }
    ],
    "location": [
        [
            {
                "param": "page",
                "operator": "==",
                "value": "31"
            }
        ]
    ],
    "menu_order": 0,
    "position": "normal",
    "style": "default",
    "label_placement": "top",
    "instruction_placement": "label",
    "hide_on_screen": [
        "the_content",
        "featured_image"
    ],
    "active": true,
    "description": "",
    "modified": 1628621977
}